MANIFEST.in
README.md
setup.py
src/ea_agents/__init__.py
src/ea_agents/plugins/__init__.py
src/ea_agents/plugins/curl/__init__.py
src/ea_agents/plugins/curl/agent_curl.py
src/ea_agents/plugins/curl/bin/curl-ca-bundle.crt
src/ea_agents/plugins/curl/bin/curl.exe
src/ea_agents/plugins/curl/bin/libcurl-x64.dll
src/extensiveautomation_agent_plugin_curl.egg-info/PKG-INFO
src/extensiveautomation_agent_plugin_curl.egg-info/SOURCES.txt
src/extensiveautomation_agent_plugin_curl.egg-info/dependency_links.txt
src/extensiveautomation_agent_plugin_curl.egg-info/requires.txt
src/extensiveautomation_agent_plugin_curl.egg-info/top_level.txt